torchsampler/__about__.py
torchsampler/__init__.py
torchsampler/imbalanced.py
torchsampler-0.1.2.dist-info/LICENSE
torchsampler-0.1.2.dist-info/METADATA
torchsampler-0.1.2.dist-info/WHEEL
torchsampler-0.1.2.dist-info/top_level.txt
torchsampler-0.1.2.dist-info/RECORD
