Metadata-Version: 2.1
Name: torchsampler
Version: 0.1.2
Summary: A (PyTorch) imbalanced dataset sampler for oversampling low classesand undersampling high frequent ones.
Home-page: https://github.com/ufoym/imbalanced-dataset-sample
Author: Ming, et al.
Author-email: a@ufoym.com
License: MIT
Keywords: sampler,pytorch,dataloader
Classifier: Environment :: Console
Classifier: Natural Language :: English
Classifier: Development Status :: 4 - Beta
Classifier: Intended Audience :: Developers
Classifier: License :: OSI Approved :: MIT License
Classifier: Operating System :: OS Independent
Classifier: Programming Language :: Python :: 3
Requires-Python: >=3.6
License-File: LICENSE
Requires-Dist: torch (>=1.3)
Requires-Dist: torchvision (>=0.5)
Requires-Dist: pandas
Requires-Dist: importlib-metadata ; python_version < "3.8"
